Workbook
Name APORTES: APP!$D$14

Sheet APP
B8: CONFIGURAÇÕES
B9: SALÁRIO | D9: 100000
B10: RENDIMENTO DA CARTEIRA | D10: 0.01
B11: SUGESTÃO DE INVESTIMENTO (30%) | D11: =D9*30% -> 30000
B13: INVESTIMENTO MENSAL
B14: QUANTO INVESTIR POR MÊS? | D14: =$D$9*30% -> 30000
B15: POR QUANTOS ANOS? | D15: 15
B16: TAXA DE RENDIMENTO MENSAL? | D16: 0.01079
B17: PATRIMÔNIO ACUMULADO? | D17: =FV(D16,D15*12,D14*-1) -> 16409358
B18: DIVIDENDO MENSAIS? | D18: =D17*1% -> 164093.58
B20: CENÁRIOS | D20: DIVIDENDOS
B21: QUANTO EM 2 ANOS? | C21: =FV($D$16,2*12,$D$14*-1) -> 816828.82 | D21: =C21*$D$10 -> 8168.2882
B22: QUANTO EM 5 ANOS? | C22: =FV($D$16,5*12,$D$14*-1) -> 2513307.4 | D22: =C22*$D$10 -> 25133.074
B23: QUANTO EM 10 ANOS? | C23: =FV($D$16,10*12,$D$14*-1) -> 7298526.4 | D23: =C23*$D$10 -> 72985.264
B24: QUANTO EM 20 ANOS? | C24: =FV($D$16,20*12,$D$14*-1) -> 33755952 | D24: =C24*$D$10 -> 337559.52
B25: QUANTO EM 30 ANOS? | C25: =FV($D$16,30*12,$D$14*-1) -> 1.2966509e+08 | D25: =C25*$D$10 -> 1296650.9
B27: PERFIL | C27: AGRESSIVO
B28: VALOR A SER INVESTIDO POR MÊS | C28: =APORTES -> 30000
B30: TIPO DE FII | C30: PERCENTUAL SUGERIDO | D30: VALORES
B31: PAPEL | C31: =VLOOKUP($C$27&"-"&B31,'Planilha 2'!$A$2:$D$20,4,FALSE) -> 0.3 | D31: =C31*$C$28 -> 9000
B32: TIJOLO | C32: =VLOOKUP($C$27&"-"&B32,'Planilha 2'!$A$2:$D$20,4,FALSE) -> 0.5 | D32: =C32*$C$28 -> 15000
B33: HÍBRIDOS | C33: =VLOOKUP($C$27&"-"&B33,'Planilha 2'!$A$2:$D$20,4,FALSE) -> 0.1 | D33: =C33*$C$28 -> 3000
B34: FOFs | C34: =VLOOKUP($C$27&"-"&B34,'Planilha 2'!$A$2:$D$20,4,FALSE) -> 0.1 | D34: =C34*$C$28 -> 3000
B35: DESENVOLVIMENTO | C35: =VLOOKUP($C$27&"-"&B35,'Planilha 2'!$A$2:$D$20,4,FALSE) -> 0 | D35: =C35*$C$28 -> 0
B36: HOTELARIAS | C36: =VLOOKUP($C$27&"-"&B36,'Planilha 2'!$A$2:$D$20,4,FALSE) -> 0 | D36: =C36*$C$28 -> 0
D37: =SUM(D31:D36) -> 30000

Sheet Planilha 2
A2: CHAVE | B2: PERFIL | C2: TIPOS DE FII | D2: PERCENTUAL
A3: =B3&"-"&C3 -> AGRESSIVO-PAPEL | B3: AGRESSIVO | C3: PAPEL | D3: 0.3
A4: =B4&"-"&C4 -> AGRESSIVO-TIJOLO | B4: AGRESSIVO | C4: TIJOLO | D4: 0.5
A5: =B5&"-"&C5 -> AGRESSIVO-HÍBRIDOS | B5: AGRESSIVO | C5: HÍBRIDOS | D5: 0.1
A6: =B6&"-"&C6 -> AGRESSIVO-FOFs | B6: AGRESSIVO | C6: FOFs | D6: 0.1
A7: =B7&"-"&C7 -> AGRESSIVO-DESENVOLVIMENTO | B7: AGRESSIVO | C7: DESENVOLVIMENTO | D7: 0
A8: =B8&"-"&C8 -> AGRESSIVO-HOTELARIAS | B8: AGRESSIVO | C8: HOTELARIAS | D8: 0
A9: =B9&"-"&C9 -> MODERADO-PAPEL | B9: MODERADO | C9: PAPEL | D9: 0.32
A10: =B10&"-"&C10 -> MODERADO-TIJOLO | B10: MODERADO | C10: TIJOLO | D10: 0.35
A11: =B11&"-"&C11 -> MODERADO-HÍBRIDOS | B11: MODERADO | C11: HÍBRIDOS | D11: 0.08
A12: =B12&"-"&C12 -> MODERADO-FOFs | B12: MODERADO | C12: FOFs | D12: 0.05
A13: =B13&"-"&C13 -> MODERADO-DESENVOLVIMENTO | B13: MODERADO | C13: DESENVOLVIMENTO | D13: 0.1
A14: =B14&"-"&C14 -> MODERADO-HOTELARIAS | B14: MODERADO | C14: HOTELARIAS | D14: 0.1
... A20: =B20&"-"&C20 -> CONSERVADOR-HOTELARIAS | B20: CONSERVADOR | C20: HOTELARIAS | D20: 0.1
